{
    "id": "elasticbeanstalk",
    "name": "Elastic Beanstalk",
    "url": "/elasticbeanstalk/home#/environments",
    "regional": true,
    "weight": 1,
    "short_name": null,
    "description": "Run and Manage Web Apps",
    "search_terms": [],
    "sub_services": [
        {
            "id": "environments",
            "name": "Environments",
            "url": "/elasticbeanstalk/home#/environments",
            "weight": 1,
            "short_name": null,
            "search_terms": []
        },
        {
            "id": "applications",
            "name": "Applications",
            "url": "/elasticbeanstalk/home#/applications",
            "weight": 1,
            "short_name": null,
            "search_terms": []
        },
        {
            "id": "changehistory",
            "name": "Change history",
            "url": "/elasticbeanstalk/home/changeHistory",
            "weight": 1,
            "short_name": null,
            "search_terms": []
        }
    ]
}